semicart/__init__.py
semicart/benchmark.py
semicart/cli.py
semicart/core/__init__.py
semicart/core/semicart.py
semicart/metrics/__init__.py
semicart/metrics/evaluation.py
semicart/utils/__init__.py
semicart/utils/distance.py
semicart/utils/logging.py
semicart-1.0.0.dist-info/licenses/LICENSE
semicart-1.0.0.dist-info/METADATA
semicart-1.0.0.dist-info/WHEEL
semicart-1.0.0.dist-info/entry_points.txt
semicart-1.0.0.dist-info/top_level.txt
semicart-1.0.0.dist-info/RECORD
