Metadata-Version: 2.4
Name: semicart
Version: 1.0.0
Summary: Semi-Supervised Classification and Regression Tree algorithm
Home-page: https://github.com/WeightedAI/semicart
Author: Aydin Abedinia
Author-email: abedinia.aydin@gmail.com
Project-URL: Bug Reports, https://github.com/WeightedAI/semicartissues
Project-URL: Source, https://github.com/WeightedAI/semicart
Classifier: Development Status :: 4 - Beta
Classifier: Intended Audience :: Science/Research
Classifier: License :: OSI Approved :: MIT License
Classifier: Programming Language :: Python :: 3
Classifier: Programming Language :: Python :: 3.7
Classifier: Programming Language :: Python :: 3.8
Classifier: Programming Language :: Python :: 3.9
Classifier: Programming Language :: Python :: 3.10
Classifier: Operating System :: OS Independent
Classifier: Topic :: Scientific/Engineering :: Artificial Intelligence
Requires-Python: >=3.7
License-File: LICENSE
Requires-Dist: numpy>=1.19.0
Requires-Dist: scikit-learn>=0.24.0
Requires-Dist: scipy>=1.6.0
Requires-Dist: pandas>=1.0.0
Dynamic: author
Dynamic: author-email
Dynamic: classifier
Dynamic: description
Dynamic: description-content-type
Dynamic: home-page
Dynamic: license-file
Dynamic: project-url
Dynamic: requires-dist
Dynamic: requires-python
Dynamic: summary
